Metadata-Version: 2.2
Name: MACS3
Version: 3.0.3
Summary: Model Based Analysis for ChIP-Seq data
Author-email: Tao Liu <vladimir.liu@gmail.com>, Philippa Doherty <Philippa.Doherty@RoswellPark.org>
Project-URL: Homepage, https://https://macs3-project.github.io/MACS/
Project-URL: Documentation, https://https://macs3-project.github.io/MACS/
Project-URL: Repository, https://github.com/macs3-project/MACS/
Project-URL: Issues, https://github.com/macs3-project/MACS/issues
Project-URL: Changelog, https://github.com/macs3-project/MACS/blob/master/ChangeLog
Classifier: Development Status :: 5 - Production/Stable
Classifier: Environment :: Console
Classifier: Intended Audience :: Developers
Classifier: Intended Audience :: Science/Research
Classifier: License :: OSI Approved :: BSD License
Classifier: Operating System :: MacOS :: MacOS X
Classifier: Operating System :: POSIX
Classifier: Operating System :: Unix
Classifier: Topic :: Scientific/Engineering :: Bio-Informatics
Classifier: Programming Language :: Python :: 3.9
Classifier: Programming Language :: Python :: 3.10
Classifier: Programming Language :: Python :: 3.11
Classifier: Programming Language :: Python :: 3.12
Classifier: Programming Language :: Python :: 3.13
Classifier: Programming Language :: Cython
Requires-Python: >=3.9
License-File: LICENSE
Requires-Dist: numpy>=1.25
Requires-Dist: scipy>=1.12
Requires-Dist: hmmlearn>=0.3.2
Requires-Dist: scikit-learn>=1.3
Requires-Dist: cykhash>=2.0
